lonely/__init__.py
lonely/__main__.py
lonely/cmd.py
lonely/system.py
lonely/app/__init__.py
lonely/app/go.py
lonely/app/yum_repo.py
lonely/cli/__init__.py
lonely/cli/lone.py
lonely/cli/sysinfo.py
lonely/core/__init__.py
lonely/core/lonely.py
lonely-0.0.5.dist-info/LICENSE
lonely-0.0.5.dist-info/METADATA
lonely-0.0.5.dist-info/WHEEL
lonely-0.0.5.dist-info/entry_points.txt
lonely-0.0.5.dist-info/top_level.txt
lonely-0.0.5.dist-info/RECORD
