Metadata-Version: 2.1
Name: lonely
Version: 0.0.5
Summary: A lonely package management tool.
Home-page: https://github.com/lonelyPale/lonely
Author: lonelypale
Author-email: lonelypale@126.com
License: Apache
Keywords: lonely tools
Platform: UNKNOWN
Requires-Python: >=3
Requires-Dist: fire
